redlock/__init__.py
redlock/algorithm.py
redlock/client.py
redlock/lock.py
redlock/scripts.py
redlock_ng-2.0.4.dist-info/METADATA
redlock_ng-2.0.4.dist-info/WHEEL
redlock_ng-2.0.4.dist-info/licenses/LICENSE
redlock_ng-2.0.4.dist-info/RECORD
