Metadata-Version: 2.4
Name: redlock-ng
Version: 2.0.4
Summary: Production-grade Redlock implementation for Python (Sync + Async)
License-File: LICENSE
Author: Vivek Dagar
Author-email: vivdagar@gmail.com
Requires-Python: >=3.9,<4.0
Classifier: Development Status :: 5 - Production/Stable
Classifier: Intended Audience :: Developers
Classifier: License :: OSI Approved :: MIT License
Classifier: Programming Language :: Python :: 3
Classifier: Programming Language :: Python :: 3.9
Classifier: Programming Language :: Python :: 3.10
Classifier: Programming Language :: Python :: 3.11
Classifier: Programming Language :: Python :: 3.12
Classifier: Programming Language :: Python :: 3.13
Classifier: Programming Language :: Python :: 3.14
Requires-Dist: pydantic (>=2.5.0,<3.0.0)
Requires-Dist: redis (>=5.0.0,<6.0.0)
Requires-Dist: urllib3 (<2.0.0)
